neo4ast-0.1.0.dist-info/METADATA
neo4ast-0.1.0.dist-info/metadata.json
neo4ast-0.1.0.dist-info/WHEEL
neo4ast-0.1.0.dist-info/top_level.txt
neo4ast-0.1.0.dist-info/DESCRIPTION.rst
neo4ast-0.1.0.dist-info/RECORD
neo4ast/store.py
neo4ast/__init__.py
